{
  "_format": "hh-sol-cache-2",
  "files": {
    "/home/hiram/projects/omnichain/contracts/EscrowVault.sol": {
      "lastModificationDate": 1744949476839,
      "contentHash": "683d3c8f5b5e0b4a9eeb41e4078a576d",
      "sourceName": "contracts/EscrowVault.sol",
      "solcConfig": {
        "version": "0.8.22",
        "settings": {
          "evmVersion": "paris",
          "optimizer": {
            "enabled": false,
            "runs": 200
          },
          "outputSelection": {
            "*": {
              "*": [
                "abi",
                "evm.bytecode",
                "evm.deployedBytecode",
                "evm.methodIdentifiers",
                "metadata"
              ],
              "": [
                "ast"
              ]
            }
          }
        }
      },
      "imports": [
        "@openzeppelin/contracts/access/Ownable.sol",
        "@openzeppelin/contracts/security/Pausable.sol",
        "@openzeppelin/contracts/security/ReentrancyGuard.sol"
      ],
      "versionPragmas": [
        "^0.8.17"
      ],
      "artifacts": [
        "EscrowVault",
        "IERC20",
        "IPortal"
      ]
    },
    "/home/hiram/projects/omnichain/node_modules/@openzeppelin/contracts/access/AccessControl.sol": {
      "lastModificationDate": 1744599219776,
      "contentHash": "849b15469d8e2bd01b49e6c632e448e7",
      "sourceName": "@openzeppelin/contracts/access/AccessControl.sol",
      "solcConfig": {
        "version": "0.8.20",
        "settings": {
          "evmVersion": "paris",
          "optimizer": {
            "enabled": false,
            "runs": 200
          },
          "outputSelection": {
            "*": {
              "*": [
                "abi",
                "evm.bytecode",
                "evm.deployedBytecode",
                "evm.methodIdentifiers",
                "metadata"
              ],
              "": [
                "ast"
              ]
            }
          }
        }
      },
      "imports": [
        "./IAccessControl.sol",
        "../utils/Context.sol",
        "../utils/introspection/ERC165.sol"
      ],
      "versionPragmas": [
        "^0.8.20"
      ],
      "artifacts": [
        "AccessControl"
      ]
    },
    "/home/hiram/projects/omnichain/node_modules/@openzeppelin/contracts/access/IAccessControl.sol": {
      "lastModificationDate": 1744599219976,
      "contentHash": "80621031deacf7066ec81277f9b1463a",
      "sourceName": "@openzeppelin/contracts/access/IAccessControl.sol",
      "solcConfig": {
        "version": "0.8.20",
        "settings": {
          "evmVersion": "paris",
          "optimizer": {
            "enabled": false,
            "runs": 200
          },
          "outputSelection": {
            "*": {
              "*": [
                "abi",
                "evm.bytecode",
                "evm.deployedBytecode",
                "evm.methodIdentifiers",
                "metadata"
              ],
              "": [
                "ast"
              ]
            }
          }
        }
      },
      "imports": [],
      "versionPragmas": [
        "^0.8.20"
      ],
      "artifacts": [
        "IAccessControl"
      ]
    },
    "/home/hiram/projects/omnichain/node_modules/@openzeppelin/contracts/utils/Context.sol": {
      "lastModificationDate": 1744681273669,
      "contentHash": "f07feb4a44b1a4872370da5aa70e8e46",
      "sourceName": "@openzeppelin/contracts/utils/Context.sol",
      "solcConfig": {
        "version": "0.8.22",
        "settings": {
          "evmVersion": "paris",
          "optimizer": {
            "enabled": false,
            "runs": 200
          },
          "outputSelection": {
            "*": {
              "*": [
                "abi",
                "evm.bytecode",
                "evm.deployedBytecode",
                "evm.methodIdentifiers",
                "metadata"
              ],
              "": [
                "ast"
              ]
            }
          }
        }
      },
      "imports": [],
      "versionPragmas": [
        "^0.8.0"
      ],
      "artifacts": [
        "Context"
      ]
    },
    "/home/hiram/projects/omnichain/node_modules/@openzeppelin/contracts/utils/introspection/ERC165.sol": {
      "lastModificationDate": 1744599219895,
      "contentHash": "7c03c1e37c3dc24eafb76dc2b8a5c3a6",
      "sourceName": "@openzeppelin/contracts/utils/introspection/ERC165.sol",
      "solcConfig": {
        "version": "0.8.20",
        "settings": {
          "evmVersion": "paris",
          "optimizer": {
            "enabled": false,
            "runs": 200
          },
          "outputSelection": {
            "*": {
              "*": [
                "abi",
                "evm.bytecode",
                "evm.deployedBytecode",
                "evm.methodIdentifiers",
                "metadata"
              ],
              "": [
                "ast"
              ]
            }
          }
        }
      },
      "imports": [
        "./IERC165.sol"
      ],
      "versionPragmas": [
        "^0.8.20"
      ],
      "artifacts": [
        "ERC165"
      ]
    },
    "/home/hiram/projects/omnichain/node_modules/@openzeppelin/contracts/utils/introspection/IERC165.sol": {
      "lastModificationDate": 1744681273700,
      "contentHash": "03e6768535ac4da0e9756f1d8a4a018a",
      "sourceName": "@openzeppelin/contracts/utils/introspection/IERC165.sol",
      "solcConfig": {
        "version": "0.8.22",
        "settings": {
          "evmVersion": "paris",
          "optimizer": {
            "enabled": false,
            "runs": 200
          },
          "outputSelection": {
            "*": {
              "*": [
                "abi",
                "evm.bytecode",
                "evm.deployedBytecode",
                "evm.methodIdentifiers",
                "metadata"
              ],
              "": [
                "ast"
              ]
            }
          }
        }
      },
      "imports": [],
      "versionPragmas": [
        "^0.8.0"
      ],
      "artifacts": [
        "IERC165"
      ]
    },
    "/home/hiram/projects/omnichain/node_modules/@openzeppelin/contracts/access/Ownable.sol": {
      "lastModificationDate": 1744681273708,
      "contentHash": "5a20b2cad87ddb61c7a3a6af21289e28",
      "sourceName": "@openzeppelin/contracts/access/Ownable.sol",
      "solcConfig": {
        "version": "0.8.22",
        "settings": {
          "evmVersion": "paris",
          "optimizer": {
            "enabled": false,
            "runs": 200
          },
          "outputSelection": {
            "*": {
              "*": [
                "abi",
                "evm.bytecode",
                "evm.deployedBytecode",
                "evm.methodIdentifiers",
                "metadata"
              ],
              "": [
                "ast"
              ]
            }
          }
        }
      },
      "imports": [
        "../utils/Context.sol"
      ],
      "versionPragmas": [
        "^0.8.0"
      ],
      "artifacts": [
        "Ownable"
      ]
    },
    "/home/hiram/projects/omnichain/node_modules/@openzeppelin/contracts/security/ReentrancyGuard.sol": {
      "lastModificationDate": 1744681273710,
      "contentHash": "1535f8c0c68463f8c1b5239f7584e71f",
      "sourceName": "@openzeppelin/contracts/security/ReentrancyGuard.sol",
      "solcConfig": {
        "version": "0.8.22",
        "settings": {
          "evmVersion": "paris",
          "optimizer": {
            "enabled": false,
            "runs": 200
          },
          "outputSelection": {
            "*": {
              "*": [
                "abi",
                "evm.bytecode",
                "evm.deployedBytecode",
                "evm.methodIdentifiers",
                "metadata"
              ],
              "": [
                "ast"
              ]
            }
          }
        }
      },
      "imports": [],
      "versionPragmas": [
        "^0.8.0"
      ],
      "artifacts": [
        "ReentrancyGuard"
      ]
    },
    "/home/hiram/projects/omnichain/node_modules/@openzeppelin/contracts/security/Pausable.sol": {
      "lastModificationDate": 1744681273708,
      "contentHash": "25c8108f36fdd472bc78d4c4af240c11",
      "sourceName": "@openzeppelin/contracts/security/Pausable.sol",
      "solcConfig": {
        "version": "0.8.22",
        "settings": {
          "evmVersion": "paris",
          "optimizer": {
            "enabled": false,
            "runs": 200
          },
          "outputSelection": {
            "*": {
              "*": [
                "abi",
                "evm.bytecode",
                "evm.deployedBytecode",
                "evm.methodIdentifiers",
                "metadata"
              ],
              "": [
                "ast"
              ]
            }
          }
        }
      },
      "imports": [
        "../utils/Context.sol"
      ],
      "versionPragmas": [
        "^0.8.0"
      ],
      "artifacts": [
        "Pausable"
      ]
    },
    "/home/hiram/projects/omnichain/node_modules/@openzeppelin/contracts/token/ERC1155/IERC1155.sol": {
      "lastModificationDate": 1744681273698,
      "contentHash": "93aa9af4f5d2d2095a71ccde917038bb",
      "sourceName": "@openzeppelin/contracts/token/ERC1155/IERC1155.sol",
      "solcConfig": {
        "version": "0.8.22",
        "settings": {
          "evmVersion": "paris",
          "optimizer": {
            "enabled": false,
            "runs": 200
          },
          "outputSelection": {
            "*": {
              "*": [
                "abi",
                "evm.bytecode",
                "evm.deployedBytecode",
                "evm.methodIdentifiers",
                "metadata"
              ],
              "": [
                "ast"
              ]
            }
          }
        }
      },
      "imports": [
        "../../utils/introspection/IERC165.sol"
      ],
      "versionPragmas": [
        "^0.8.0"
      ],
      "artifacts": [
        "IERC1155"
      ]
    },
    "/home/hiram/projects/omnichain/node_modules/@openzeppelin/contracts/token/ERC1155/IERC1155Receiver.sol": {
      "lastModificationDate": 1744681273699,
      "contentHash": "9f8822b72fe2702979e40160cb6d9636",
      "sourceName": "@openzeppelin/contracts/token/ERC1155/IERC1155Receiver.sol",
      "solcConfig": {
        "version": "0.8.22",
        "settings": {
          "evmVersion": "paris",
          "optimizer": {
            "enabled": false,
            "runs": 200
          },
          "outputSelection": {
            "*": {
              "*": [
                "abi",
                "evm.bytecode",
                "evm.deployedBytecode",
                "evm.methodIdentifiers",
                "metadata"
              ],
              "": [
                "ast"
              ]
            }
          }
        }
      },
      "imports": [
        "../../utils/introspection/IERC165.sol"
      ],
      "versionPragmas": [
        "^0.8.0"
      ],
      "artifacts": [
        "IERC1155Receiver"
      ]
    },
    "/home/hiram/projects/omnichain/node_modules/@openzeppelin/contracts/token/ERC721/IERC721.sol": {
      "lastModificationDate": 1744681273704,
      "contentHash": "48de4c9a3a4ae5ef66a2aa620843413f",
      "sourceName": "@openzeppelin/contracts/token/ERC721/IERC721.sol",
      "solcConfig": {
        "version": "0.8.22",
        "settings": {
          "evmVersion": "paris",
          "optimizer": {
            "enabled": false,
            "runs": 200
          },
          "outputSelection": {
            "*": {
              "*": [
                "abi",
                "evm.bytecode",
                "evm.deployedBytecode",
                "evm.methodIdentifiers",
                "metadata"
              ],
              "": [
                "ast"
              ]
            }
          }
        }
      },
      "imports": [
        "../../utils/introspection/IERC165.sol"
      ],
      "versionPragmas": [
        "^0.8.0"
      ],
      "artifacts": [
        "IERC721"
      ]
    },
    "/home/hiram/projects/omnichain/node_modules/@openzeppelin/contracts/token/ERC721/IERC721Receiver.sol": {
      "lastModificationDate": 1744681273704,
      "contentHash": "c22d4395e33763de693fd440c6fd10e1",
      "sourceName": "@openzeppelin/contracts/token/ERC721/IERC721Receiver.sol",
      "solcConfig": {
        "version": "0.8.22",
        "settings": {
          "evmVersion": "paris",
          "optimizer": {
            "enabled": false,
            "runs": 200
          },
          "outputSelection": {
            "*": {
              "*": [
                "abi",
                "evm.bytecode",
                "evm.deployedBytecode",
                "evm.methodIdentifiers",
                "metadata"
              ],
              "": [
                "ast"
              ]
            }
          }
        }
      },
      "imports": [],
      "versionPragmas": [
        "^0.8.0"
      ],
      "artifacts": [
        "IERC721Receiver"
      ]
    }
  }
}
